pulumi_temporalcloud/__init__.py
pulumi_temporalcloud/_inputs.py
pulumi_temporalcloud/_utilities.py
pulumi_temporalcloud/apikey.py
pulumi_temporalcloud/get_namespaces.py
pulumi_temporalcloud/get_regions.py
pulumi_temporalcloud/get_service_accounts.py
pulumi_temporalcloud/metrics_endpoint.py
pulumi_temporalcloud/namespace.py
pulumi_temporalcloud/namespace_search_attribute.py
pulumi_temporalcloud/nexus_endpoint.py
pulumi_temporalcloud/outputs.py
pulumi_temporalcloud/provider.py
pulumi_temporalcloud/pulumi-plugin.json
pulumi_temporalcloud/py.typed
pulumi_temporalcloud/service_account.py
pulumi_temporalcloud/user.py
pulumi_temporalcloud/config/__init__.py
pulumi_temporalcloud/config/__init__.pyi
pulumi_temporalcloud/config/vars.py
pulumi_temporalcloud-0.6.2.dist-info/METADATA
pulumi_temporalcloud-0.6.2.dist-info/WHEEL
pulumi_temporalcloud-0.6.2.dist-info/top_level.txt
pulumi_temporalcloud-0.6.2.dist-info/RECORD
